pscrap/__init__.py
pscrap/__main__.py
pscrap-1.0.0.dist-info/LICENSE
pscrap-1.0.0.dist-info/METADATA
pscrap-1.0.0.dist-info/WHEEL
pscrap-1.0.0.dist-info/entry_points.txt
pscrap-1.0.0.dist-info/top_level.txt
pscrap-1.0.0.dist-info/RECORD
