Metadata-Version: 2.1
Name: pscrap
Version: 1.0.0
Summary: multi processed parameter scrapper
Home-page: https://github.com/root-tanishq/pscrap
Author: Tanishq Rathore
License: MIT
Classifier: Programming Language :: Python :: 3
License-File: LICENSE
Requires-Dist: requests
